LICENSE
MANIFEST.in
README.md
setup.py
django_aliyun_oss2/__init__.py
django_aliyun_oss2/backends.py
django_aliyun_oss2.egg-info/PKG-INFO
django_aliyun_oss2.egg-info/SOURCES.txt
django_aliyun_oss2.egg-info/dependency_links.txt
django_aliyun_oss2.egg-info/requires.txt
django_aliyun_oss2.egg-info/top_level.txt